nonebot_plugin_wwgachalogs/__init__.py
nonebot_plugin_wwgachalogs/config.py
nonebot_plugin_wwgachalogs/db.py
nonebot_plugin_wwgachalogs/gacha.py
nonebot_plugin_wwgachalogs/migrations/2e188b3f6e5b_first_revision.py
nonebot_plugin_wwgachalogs/model.py
nonebot_plugin_wwgachalogs-0.1.7.dist-info/LICENSE
nonebot_plugin_wwgachalogs-0.1.7.dist-info/METADATA
nonebot_plugin_wwgachalogs-0.1.7.dist-info/WHEEL
nonebot_plugin_wwgachalogs-0.1.7.dist-info/RECORD
