Metadata-Version: 2.1
Name: nonebot-plugin-wwgachalogs
Version: 0.1.7
Summary: 
License: MIT
Author: irelia
Requires-Python: >=3.10,<4.0
Classifier: License :: OSI Approved :: MIT License
Classifier: Programming Language :: Python :: 3
Classifier: Programming Language :: Python :: 3.10
Classifier: Programming Language :: Python :: 3.11
Classifier: Programming Language :: Python :: 3.12
Requires-Dist: httpx (>=0.27.0,<0.28.0)
Requires-Dist: nonebot-adapter-onebot (>=2.4.3,<3.0.0)
Requires-Dist: nonebot-plugin-orm[aiosqlite] (>=0.7.3,<0.8.0)
Requires-Dist: nonebot-plugin-saalc (>=0.1.1,<0.2.0)
Requires-Dist: nonebot2 (>=2.3.1,<3.0.0)
Requires-Dist: sqlalchemy (>=2.0.30,<3.0.0)
